pydantic_discriminator/__init__.py
pydantic_discriminator/base_v1.py
pydantic_discriminator/base_v2.py
pydantic_discriminator/common.py
pydantic_discriminator-0.1.0.dist-info/METADATA
pydantic_discriminator-0.1.0.dist-info/WHEEL
pydantic_discriminator-0.1.0.dist-info/licenses/LICENSE
pydantic_discriminator-0.1.0.dist-info/RECORD
