Metadata-Version: 2.1
Name: pydantic-discriminator
Version: 0.1.0
Summary: Pydantic discriminators for polymorphic models
Project-URL: Repository, https://github.com/lucabonfiglioli/pydantic-discriminator
Author-email: Luca Bonfiglioli <luca.bonfiglioli@gmail.com>
Maintainer-email: Luca Bonfiglioli <luca.bonfiglioli@gmail.com>
License: This is free and unencumbered software released into the public domain.
License-File: LICENSE
Keywords: discriminator,polymorphism,pydantic
Classifier: Development Status :: 4 - Beta
Classifier: Programming Language :: Python
Requires-Python: >=3.9
Requires-Dist: packaging
Requires-Dist: pydantic<3.0,>=1.10
Provides-Extra: dev
Requires-Dist: black; extra == 'dev'
Requires-Dist: build; extra == 'dev'
Requires-Dist: deepdiff; extra == 'dev'
Requires-Dist: flake8; extra == 'dev'
Requires-Dist: pytest; extra == 'dev'
Requires-Dist: pytest-cov; extra == 'dev'
Requires-Dist: tox; extra == 'dev'
Requires-Dist: tox-conda; extra == 'dev'
